<?xml version="1.0" encoding="utf-8" ?>
<dwsync>
<file name="getMyTime().js" server="79175.w75.wedos.net" local="131020779656149461" remote="131196354600000000" Dst="2" />
<file name="getMyTime().php" server="79175.w75.wedos.net" local="131188017365540516" remote="131196354600000000" Dst="2" />
<file name="mail.php" server="79175.w75.wedos.net" local="131001935877383746" remote="131196354600000000" Dst="2" />
<file name="platba.php" server="79175.w75.wedos.net" local="131244885380290085" remote="131244849000000000" Dst="1" />
<file name="pridat.php" server="79175.w75.wedos.net" local="131479904984571014" remote="131479836600000000" Dst="2" />
<file name="stare_ucty.php" server="79175.w75.wedos.net" local="131242352866342812" remote="131242317000000000" Dst="1" />
<file name="styly.css" server="79175.w75.wedos.net" local="131483390051538534" remote="131483364000000000" Dst="2" />
<file name="uvod.php" server="79175.w75.wedos.net" local="131483160176713712" remote="131483088000000000" Dst="2" />
<file name="sortForm.php" server="79175.w75.wedos.net" local="131242353021913377" remote="131242317000000000" Dst="1" />
<file name="admin.php" server="79175.w75.wedos.net" local="131242272177799046" remote="131242236000000000" Dst="1" />
<file name="settings.php" server="79175.w75.wedos.net" local="131483339090605808" remote="131483364000000000" Dst="2" />
</dwsync>