<?xml version="1.0" encoding="utf-8" ?>
<dwsync>
<file name="back.png" server="79175.w75.wedos.net" local="131112500668817839" remote="131112504600000000" Dst="2" />
<file name="setToReat.png" server="79175.w75.wedos.net" local="131112571640808433" remote="131112504600000000" Dst="2" />
<file name="setToUnreat.png" server="79175.w75.wedos.net" local="131112573150746389" remote="131112504600000000" Dst="2" />
<file name="inBox.png" server="79175.w75.wedos.net" local="131112511002252690" remote="131112504600000000" Dst="2" />
<file name="spam.png" server="79175.w75.wedos.net" local="131112497221746613" remote="131112504600000000" Dst="2" />
<file name="toBin.png" server="79175.w75.wedos.net" local="131112497861877948" remote="131112504600000000" Dst="2" />
<file name="delete.png" server="79175.w75.wedos.net" local="131112501364263035" remote="131112504600000000" Dst="2" />
<file name="reply.png" server="79175.w75.wedos.net" local="131112698542206825" remote="131112710400000000" Dst="2" />
<file name="reSend.png" server="79175.w75.wedos.net" local="131112698901255952" remote="131112710400000000" Dst="2" />
</dwsync>